Metadata-Version: 2.1
Name: vatsalS3
Version: 0.1.0
Summary: Basic S3 operations
Home-page: https://github.com/vatsal1306/vatsalS3
Author: Vatsal Vadodaria
Author-email: vatsal1399@gmail.com
Classifier: Development Status :: 3 - Alpha
Classifier: Intended Audience :: Developers
Classifier: License :: OSI Approved :: MIT License
Classifier: Programming Language :: Python :: 3.11
Requires-Python: >=3.9
License-File: LICENSE
Requires-Dist: boto3==1.34.143
Requires-Dist: botocore==1.34.143
